LICENSE
MANIFEST.in
README.md
setup.cfg
setup.py
src/flask_MenuManager/__init__.py
src/flask_MenuManager.egg-info/PKG-INFO
src/flask_MenuManager.egg-info/SOURCES.txt
src/flask_MenuManager.egg-info/dependency_links.txt
src/flask_MenuManager.egg-info/not-zip-safe
src/flask_MenuManager.egg-info/requires.txt
src/flask_MenuManager.egg-info/top_level.txt