Metadata-Version: 1.0
Name: flask-MenuManager
Version: 1.0a2
Summary: An easy way to build and manage menus in Flask
Home-page: https://svn.apache.org/repos/asf/labs/panopticon/
Author: Alan Cabrera
Author-email: adc@toolazydogs.com
License: Apache License (http://www.apache.org/licenses/LICENSE-2.0)
Platform: any
Classifier: Environment :: Web Environment
Classifier: Intended Audience :: Developers
Classifier: License :: OSI Approved :: BSD License
Classifier: Operating System :: OS Independent
Classifier: Topic :: Internet :: WWW/HTTP :: Dynamic Content
Classifier: Topic :: Software Development :: Libraries :: Python Modules
Classifier: Programming Language :: Python
Classifier: Programming Language :: Python :: 2
Classifier: Programming Language :: Python :: 2.6
Classifier: Programming Language :: Python :: 2.7
Classifier: Programming Language :: Python :: 3
Classifier: Programming Language :: Python :: 3.3
Classifier: Programming Language :: Python :: 3.4
